{
    "single_trivia_dev_1002": {
        "option": "A",
        "prediction": "Australia and New Zealand",
        "stepNum": 0
    },
    "single_trivia_dev_1007": {
        "option": "B",
        "prediction": "Nova Scotia",
        "stepNum": 1
    },
    "single_trivia_dev_1012": {
        "option": "B",
        "prediction": "8 feet",
        "stepNum": 1
    },
    "single_trivia_dev_1035": {
        "option": "B",
        "prediction": "France and Italy",
        "stepNum": 1
    },
    "single_trivia_dev_1038": {
        "option": "B",
        "prediction": "Lal Bahadur Shastri",
        "stepNum": 1
    },
    "single_trivia_dev_1071": {
        "option": "B",
        "prediction": "a train",
        "stepNum": 1
    },
    "single_trivia_dev_1089": {
        "option": "B",
        "prediction": "Feeble",
        "stepNum": 1
    },
    "single_trivia_dev_1103": {
        "option": "B",
        "prediction": "Minnesota",
        "stepNum": 1
    },
    "single_trivia_dev_1109": {
        "option": "A",
        "prediction": "Argentina",
        "stepNum": 0
    },
    "single_trivia_dev_111": {
        "option": "B",
        "prediction": "Beatrix of the Netherlands",
        "stepNum": 1
    },
    "single_trivia_dev_1132": {
        "option": "B",
        "prediction": "Lao kip",
        "stepNum": 1
    },
    "single_trivia_dev_1160": {
        "option": "A",
        "prediction": "fish",
        "stepNum": 0
    },
    "single_trivia_dev_1188": {
        "option": "B",
        "prediction": "The poltergeist which haunts Hogwarts School in the Harry Potter series of novels is Peeves. However, Peeves is not mentioned in the provided text. The text does mention that the game \\\"Harry Potter: Hogwarts Mystery\\\" features a customisable protagonist who can interact with notable characters from the series such as Albus Dumbledore, Rubeus Hagrid, and Peeves is not mentioned. However, the text does mention that the game features a character named Peeves. So the answer is:",
        "stepNum": 1
    },
    "single_trivia_dev_1202": {
        "option": "A",
        "prediction": "Manchester United",
        "stepNum": 0
    },
    "single_trivia_dev_1208": {
        "option": "B",
        "prediction": "Amir Khan",
        "stepNum": 1
    },
    "single_trivia_dev_1229": {
        "option": "A",
        "prediction": "Batgirl",
        "stepNum": 0
    },
    "single_trivia_dev_1238": {
        "option": "B",
        "prediction": "There is no answer",
        "stepNum": 1
    },
    "single_trivia_dev_1247": {
        "option": "A",
        "prediction": "swan song",
        "stepNum": 0
    },
    "single_trivia_dev_1253": {
        "option": "B",
        "prediction": "gold coin, gold bullion, and gold certificates",
        "stepNum": 1
    },
    "single_trivia_dev_1329": {
        "option": "B",
        "prediction": "brown",
        "stepNum": 1
    },
    "single_trivia_dev_135": {
        "option": "B",
        "prediction": "Love Field",
        "stepNum": 1
    },
    "single_trivia_dev_1378": {
        "option": "B",
        "prediction": "There is no answer",
        "stepNum": 1
    },
    "single_trivia_dev_1381": {
        "option": "B",
        "prediction": "Carmen Miranda",
        "stepNum": 1
    },
    "single_trivia_dev_139": {
        "option": "B",
        "prediction": "neighbourhood, city, ward, drive, and sanctuary",
        "stepNum": 1
    },
    "single_trivia_dev_1392": {
        "option": "B",
        "prediction": "None",
        "stepNum": 1
    },
    "single_trivia_dev_1436": {
        "option": "B",
        "prediction": "Elizabeth Dawn",
        "stepNum": 1
    },
    "single_trivia_dev_144": {
        "option": "B",
        "prediction": "Battle Creek Sanitarium",
        "stepNum": 1
    },
    "single_trivia_dev_1442": {
        "option": "A",
        "prediction": "limestone",
        "stepNum": 0
    },
    "single_trivia_dev_1458": {
        "option": "B",
        "prediction": "ions",
        "stepNum": 1
    },
    "single_trivia_dev_1481": {
        "option": "C",
        "prediction": "County Donegal",
        "stepNum": 2
    },
    "single_trivia_dev_1500": {
        "option": "B",
        "prediction": "Pluto",
        "stepNum": 1
    },
    "single_trivia_dev_1518": {
        "option": "C",
        "prediction": "Swiss-British",
        "stepNum": 2
    },
    "single_trivia_dev_1553": {
        "option": "B",
        "prediction": "Griswold",
        "stepNum": 1
    },
    "single_trivia_dev_1557": {
        "option": "B",
        "prediction": "biscuit",
        "stepNum": 1
    },
    "single_trivia_dev_1567": {
        "option": "B",
        "prediction": "Beef Stroganoff",
        "stepNum": 1
    },
    "single_trivia_dev_1575": {
        "option": "A",
        "prediction": "Manchester City",
        "stepNum": 0
    },
    "single_trivia_dev_1579": {
        "option": "B",
        "prediction": "Wyoming",
        "stepNum": 1
    },
    "single_trivia_dev_159": {
        "option": "B",
        "prediction": "Texas",
        "stepNum": 1
    },
    "single_trivia_dev_1612": {
        "option": "B",
        "prediction": "Bottom",
        "stepNum": 1
    },
    "single_trivia_dev_1618": {
        "option": "A",
        "prediction": "Toad",
        "stepNum": 0
    },
    "single_trivia_dev_1631": {
        "option": "B",
        "prediction": "Northumberland",
        "stepNum": 1
    },
    "single_trivia_dev_1635": {
        "option": "B",
        "prediction": "the Supreme Being",
        "stepNum": 1
    },
    "single_trivia_dev_1644": {
        "option": "B",
        "prediction": "Mr. Niebla",
        "stepNum": 1
    },
    "single_trivia_dev_1649": {
        "option": "A",
        "prediction": "Shenandoah",
        "stepNum": 0
    },
    "single_trivia_dev_1655": {
        "option": "B",
        "prediction": "None",
        "stepNum": 1
    },
    "single_trivia_dev_167": {
        "option": "B",
        "prediction": "Johnny Depp",
        "stepNum": 1
    },
    "single_trivia_dev_1677": {
        "option": "B",
        "prediction": "Emperor Franz Joseph I",
        "stepNum": 1
    },
    "single_trivia_dev_1713": {
        "option": "A",
        "prediction": "Ovaltine",
        "stepNum": 0
    },
    "single_trivia_dev_173": {
        "option": "B",
        "prediction": "There is no answer",
        "stepNum": 1
    },
    "single_trivia_dev_1735": {
        "option": "B",
        "prediction": "John J. Pershing",
        "stepNum": 1
    },
    "single_trivia_dev_1746": {
        "option": "B",
        "prediction": "None",
        "stepNum": 1
    },
    "single_trivia_dev_1759": {
        "option": "B",
        "prediction": "King Henry VI",
        "stepNum": 1
    },
    "single_trivia_dev_1780": {
        "option": "A",
        "prediction": "Richard II",
        "stepNum": 0
    },
    "single_trivia_dev_1818": {
        "option": "B",
        "prediction": "a dove",
        "stepNum": 1
    },
    "single_trivia_dev_1866": {
        "option": "B",
        "prediction": "Paperback Writer",
        "stepNum": 1
    },
    "single_trivia_dev_1880": {
        "option": "B",
        "prediction": "clarinet, soprano saxophone, tenor saxophone, piano, bass, and drums",
        "stepNum": 1
    },
    "single_trivia_dev_1886": {
        "option": "B",
        "prediction": "Gal\\u00e1pagos Islands",
        "stepNum": 1
    },
    "single_trivia_dev_1893": {
        "option": "A",
        "prediction": "August 15, 1945",
        "stepNum": 0
    },
    "single_trivia_dev_19": {
        "option": "B",
        "prediction": "United States",
        "stepNum": 1
    },
    "single_trivia_dev_1919": {
        "option": "B",
        "prediction": "The winner of the 2011 BBC Sports Personality of the Year Award was Mark Cavendish. The nominees and their achievements in 2011 as described by the BBC and their share of the votes cast were as follows: Mark Cavendish, the British cyclist, won the award with 35.6% of the vote. The other nominees were: Bradley Wiggins, the British cyclist, who won the Tour de France; Chris Froome, the British cyclist, who won the Vuel",
        "stepNum": 1
    },
    "single_trivia_dev_194": {
        "option": "B",
        "prediction": "Armenia",
        "stepNum": 1
    },
    "single_trivia_dev_1950": {
        "option": "B",
        "prediction": "Gary Barlow",
        "stepNum": 1
    },
    "single_trivia_dev_197": {
        "option": "B",
        "prediction": "Sharpeville",
        "stepNum": 1
    },
    "single_trivia_dev_1992": {
        "option": "A",
        "prediction": "Plymouth",
        "stepNum": 0
    },
    "single_trivia_dev_1996": {
        "option": "B",
        "prediction": "Coal Miner's Daughter",
        "stepNum": 1
    },
    "single_trivia_dev_2028": {
        "option": "B",
        "prediction": "2",
        "stepNum": 1
    },
    "single_trivia_dev_2038": {
        "option": "B",
        "prediction": "None",
        "stepNum": 1
    },
    "single_trivia_dev_2043": {
        "option": "A",
        "prediction": "Ryan Moore",
        "stepNum": 0
    },
    "single_trivia_dev_2051": {
        "option": "B",
        "prediction": "Beef Stroganoff",
        "stepNum": 1
    },
    "single_trivia_dev_2059": {
        "option": "B",
        "prediction": "There is no connection",
        "stepNum": 1
    },
    "single_trivia_dev_2075": {
        "option": "A",
        "prediction": "Kiev",
        "stepNum": 0
    },
    "single_trivia_dev_2094": {
        "option": "A",
        "prediction": "Paul Emsley",
        "stepNum": 0
    },
    "single_trivia_dev_2114": {
        "option": "C",
        "prediction": "Harry Palmer",
        "stepNum": 2
    },
    "single_trivia_dev_2116": {
        "option": "B",
        "prediction": "Antony",
        "stepNum": 1
    },
    "single_trivia_dev_2125": {
        "option": "B",
        "prediction": "Electric Light Orchestra",
        "stepNum": 1
    },
    "single_trivia_dev_2139": {
        "option": "B",
        "prediction": "Trajan",
        "stepNum": 1
    },
    "single_trivia_dev_2153": {
        "option": "C",
        "prediction": "Cairn Gorm",
        "stepNum": 10
    },
    "single_trivia_dev_2175": {
        "option": "B",
        "prediction": "Ivor Novello",
        "stepNum": 1
    },
    "single_trivia_dev_219": {
        "option": "B",
        "prediction": "materials at very low temperatures",
        "stepNum": 1
    },
    "single_trivia_dev_2194": {
        "option": "A",
        "prediction": "Peter Purves",
        "stepNum": 0
    },
    "single_trivia_dev_2222": {
        "option": "B",
        "prediction": "8",
        "stepNum": 1
    },
    "single_trivia_dev_2225": {
        "option": "B",
        "prediction": "England",
        "stepNum": 1
    },
    "single_trivia_dev_2253": {
        "option": "C",
        "prediction": "26,000",
        "stepNum": 2
    },
    "single_trivia_dev_2272": {
        "option": "A",
        "prediction": "firmware",
        "stepNum": 0
    },
    "single_trivia_dev_229": {
        "option": "B",
        "prediction": "water",
        "stepNum": 1
    },
    "single_trivia_dev_2301": {
        "option": "B",
        "prediction": "Amy Williams",
        "stepNum": 1
    },
    "single_trivia_dev_2306": {
        "option": "C",
        "prediction": "Union of European Football Associations",
        "stepNum": 2
    },
    "single_trivia_dev_2329": {
        "option": "B",
        "prediction": "calcium",
        "stepNum": 1
    },
    "single_trivia_dev_233": {
        "option": "A",
        "prediction": "crust",
        "stepNum": 0
    },
    "single_trivia_dev_2362": {
        "option": "B",
        "prediction": "Bayer",
        "stepNum": 1
    },
    "single_trivia_dev_24": {
        "option": "B",
        "prediction": "Royal Canadian Air Force",
        "stepNum": 1
    },
    "single_trivia_dev_2409": {
        "option": "A",
        "prediction": "law",
        "stepNum": 0
    },
    "single_trivia_dev_2410": {
        "option": "A",
        "prediction": "human qualities",
        "stepNum": 0
    },
    "single_trivia_dev_2442": {
        "option": "B",
        "prediction": "habitable zone",
        "stepNum": 1
    },
    "single_trivia_dev_2498": {
        "option": "A",
        "prediction": "square",
        "stepNum": 0
    },
    "single_trivia_dev_2513": {
        "option": "B",
        "prediction": "Prince George, Duke of Cambridge",
        "stepNum": 1
    },
    "single_trivia_dev_2566": {
        "option": "A",
        "prediction": "Type 55",
        "stepNum": 0
    },
    "single_trivia_dev_2572": {
        "option": "C",
        "prediction": "737.28",
        "stepNum": 2
    },
    "single_trivia_dev_2575": {
        "option": "B",
        "prediction": "sulfur",
        "stepNum": 1
    },
    "single_trivia_dev_2581": {
        "option": "B",
        "prediction": "Salsify",
        "stepNum": 1
    },
    "single_trivia_dev_2583": {
        "option": "B",
        "prediction": "waterproof fabric",
        "stepNum": 1
    },
    "single_trivia_dev_2598": {
        "option": "B",
        "prediction": "jambalaya",
        "stepNum": 1
    },
    "single_trivia_dev_2609": {
        "option": "A",
        "prediction": "practice",
        "stepNum": 0
    },
    "single_trivia_dev_2613": {
        "option": "A",
        "prediction": "Zinc",
        "stepNum": 0
    },
    "single_trivia_dev_2616": {
        "option": "C",
        "prediction": "ballet",
        "stepNum": 2
    },
    "single_trivia_dev_2617": {
        "option": "C",
        "prediction": "chewing",
        "stepNum": 2
    },
    "single_trivia_dev_2619": {
        "option": "B",
        "prediction": "Rolling Stone",
        "stepNum": 1
    },
    "single_trivia_dev_2654": {
        "option": "B",
        "prediction": "Windows logo",
        "stepNum": 1
    },
    "single_trivia_dev_2658": {
        "option": "C",
        "prediction": "yes",
        "stepNum": 2
    },
    "single_trivia_dev_2661": {
        "option": "C",
        "prediction": "Neptune",
        "stepNum": 3
    },
    "single_trivia_dev_2664": {
        "option": "B",
        "prediction": "Volkswagen",
        "stepNum": 1
    },
    "single_trivia_dev_2665": {
        "option": "B",
        "prediction": "Back to the Future",
        "stepNum": 1
    },
    "single_trivia_dev_2675": {
        "option": "C",
        "prediction": "France",
        "stepNum": 2
    },
    "single_trivia_dev_2685": {
        "option": "C",
        "prediction": "LinkedIn",
        "stepNum": 2
    },
    "single_trivia_dev_2698": {
        "option": "A",
        "prediction": "ore",
        "stepNum": 0
    },
    "single_trivia_dev_2702": {
        "option": "A",
        "prediction": "prestige",
        "stepNum": 0
    },
    "single_trivia_dev_2704": {
        "option": "A",
        "prediction": "screw drives",
        "stepNum": 0
    },
    "single_trivia_dev_2708": {
        "option": "B",
        "prediction": "Asperitas",
        "stepNum": 1
    },
    "single_trivia_dev_2771": {
        "option": "A",
        "prediction": "Croatia",
        "stepNum": 0
    },
    "single_trivia_dev_2773": {
        "option": "B",
        "prediction": "Glasgow",
        "stepNum": 1
    },
    "single_trivia_dev_2799": {
        "option": "B",
        "prediction": "Albert Einstein",
        "stepNum": 1
    },
    "single_trivia_dev_2805": {
        "option": "B",
        "prediction": "Leonard Cohen",
        "stepNum": 1
    },
    "single_trivia_dev_2820": {
        "option": "A",
        "prediction": "Tigris and Euphrates",
        "stepNum": 0
    },
    "single_trivia_dev_2829": {
        "option": "B",
        "prediction": "There is no answer to this question",
        "stepNum": 1
    },
    "single_trivia_dev_2839": {
        "option": "B",
        "prediction": "Blondin",
        "stepNum": 1
    },
    "single_trivia_dev_2849": {
        "option": "C",
        "prediction": "Norwegian",
        "stepNum": 2
    },
    "single_trivia_dev_2854": {
        "option": "B",
        "prediction": "Ernest Hemingway",
        "stepNum": 1
    },
    "single_trivia_dev_2856": {
        "option": "A",
        "prediction": "a Polish folk dance",
        "stepNum": 0
    },
    "single_trivia_dev_2857": {
        "option": "B",
        "prediction": "familiar faces",
        "stepNum": 1
    },
    "single_trivia_dev_2871": {
        "option": "B",
        "prediction": "Gannex",
        "stepNum": 1
    },
    "single_trivia_dev_2888": {
        "option": "B",
        "prediction": "Not mentioned in the text",
        "stepNum": 1
    },
    "single_trivia_dev_2912": {
        "option": "B",
        "prediction": "Neva River",
        "stepNum": 1
    },
    "single_trivia_dev_2927": {
        "option": "A",
        "prediction": "spider",
        "stepNum": 0
    },
    "single_trivia_dev_2987": {
        "option": "B",
        "prediction": "international acclaim",
        "stepNum": 1
    },
    "single_trivia_dev_304": {
        "option": "B",
        "prediction": "1987",
        "stepNum": 1
    },
    "single_trivia_dev_3058": {
        "option": "B",
        "prediction": "the number of stars and the color of the stars",
        "stepNum": 1
    },
    "single_trivia_dev_3061": {
        "option": "C",
        "prediction": "Laureate Hospitality Education",
        "stepNum": 2
    },
    "single_trivia_dev_3083": {
        "option": "A",
        "prediction": "Auckland Harbour",
        "stepNum": 0
    },
    "single_trivia_dev_3086": {
        "option": "A",
        "prediction": "Maxim Gorky",
        "stepNum": 0
    },
    "single_trivia_dev_3094": {
        "option": "A",
        "prediction": "Olympic Stadium",
        "stepNum": 0
    },
    "single_trivia_dev_3122": {
        "option": "C",
        "prediction": "giving birth to octuplets",
        "stepNum": 2
    },
    "single_trivia_dev_3126": {
        "option": "B",
        "prediction": "U.S. Virgin Islands",
        "stepNum": 1
    },
    "single_trivia_dev_3151": {
        "option": "B",
        "prediction": "Washington, D.C",
        "stepNum": 1
    },
    "single_trivia_dev_3201": {
        "option": "A",
        "prediction": "The \\\"seven Champions of Christendom\\\" were St George, St Andrew, St David, St Patrick, St Denys, St James and St George's companion St George's companion is St George's companion is St George's companion is St George's companion is St George's companion is St George's companion is St George's companion is St George's companion is St George's companion is St George's companion is St George's companion is St George's companion is St George's companion is St George",
        "stepNum": 0
    },
    "single_trivia_dev_3217": {
        "option": "A",
        "prediction": "Eritrea",
        "stepNum": 0
    },
    "single_trivia_dev_3219": {
        "option": "B",
        "prediction": "reptile",
        "stepNum": 1
    },
    "single_trivia_dev_3225": {
        "option": "A",
        "prediction": "Pinochle",
        "stepNum": 0
    },
    "single_trivia_dev_3233": {
        "option": "A",
        "prediction": "openness and restructuring",
        "stepNum": 0
    },
    "single_trivia_dev_3274": {
        "option": "B",
        "prediction": "aberration of light",
        "stepNum": 1
    },
    "single_trivia_dev_3301": {
        "option": "B",
        "prediction": "Hank Marvin",
        "stepNum": 1
    },
    "single_trivia_dev_3305": {
        "option": "B",
        "prediction": "Jacques Cartier",
        "stepNum": 1
    },
    "single_trivia_dev_3328": {
        "option": "A",
        "prediction": "swimsuit",
        "stepNum": 0
    },
    "single_trivia_dev_3336": {
        "option": "B",
        "prediction": "Lake Michigan",
        "stepNum": 1
    },
    "single_trivia_dev_3345": {
        "option": "B",
        "prediction": "Faisal I of Iraq",
        "stepNum": 1
    },
    "single_trivia_dev_3353": {
        "option": "B",
        "prediction": "Nineteen Eighty-Four",
        "stepNum": 1
    },
    "single_trivia_dev_3379": {
        "option": "B",
        "prediction": "fraction bar",
        "stepNum": 1
    },
    "single_trivia_dev_3409": {
        "option": "B",
        "prediction": "Argentina",
        "stepNum": 1
    },
    "single_trivia_dev_3432": {
        "option": "B",
        "prediction": "134",
        "stepNum": 1
    },
    "single_trivia_dev_3437": {
        "option": "B",
        "prediction": "Saint Kentigern, or Mungo",
        "stepNum": 1
    },
    "single_trivia_dev_3477": {
        "option": "A",
        "prediction": "drunk driving",
        "stepNum": 0
    },
    "single_trivia_dev_3479": {
        "option": "A",
        "prediction": "World War II",
        "stepNum": 0
    },
    "single_trivia_dev_3486": {
        "option": "A",
        "prediction": "Saturn",
        "stepNum": 0
    },
    "single_trivia_dev_3488": {
        "option": "B",
        "prediction": "record-breaking rains",
        "stepNum": 1
    },
    "single_trivia_dev_3492": {
        "option": "A",
        "prediction": "Venice",
        "stepNum": 0
    },
    "single_trivia_dev_3500": {
        "option": "B",
        "prediction": "the western Mediterranean Sea, near the eastern coast of the Iberian Peninsula",
        "stepNum": 1
    },
    "single_trivia_dev_3503": {
        "option": "C",
        "prediction": "athletics",
        "stepNum": 1
    },
    "single_trivia_dev_3505": {
        "option": "B",
        "prediction": "octane rating",
        "stepNum": 1
    },
    "single_trivia_dev_3514": {
        "option": "A",
        "prediction": "Donatella Versace",
        "stepNum": 0
    },
    "single_trivia_dev_3525": {
        "option": "C",
        "prediction": "Curse of Tippecanoe",
        "stepNum": 2
    },
    "single_trivia_dev_3568": {
        "option": "B",
        "prediction": "Puget Sound",
        "stepNum": 1
    },
    "single_trivia_dev_3571": {
        "option": "B",
        "prediction": "When a surfer falls off the surfboard while riding a wave, it is called a wipeout. However, the text does not mention the term \\\"wipeout\\\". Instead, it mentions that the purpose of using a leg rope is to keep the surfboard attached to a surfer's ankle at a safe distance. Should the surfer fall while riding a wave, the surfboard will not get swept away by waves and stop runaway surfboards from hitting other surfers and swimmers. So the",
        "stepNum": 1
    },
    "single_trivia_dev_3608": {
        "option": "A",
        "prediction": "Asia",
        "stepNum": 0
    },
    "single_trivia_dev_3609": {
        "option": "B",
        "prediction": "none",
        "stepNum": 1
    },
    "single_trivia_dev_3620": {
        "option": "A",
        "prediction": "England",
        "stepNum": 0
    },
    "single_trivia_dev_3622": {
        "option": "B",
        "prediction": "the assassination of President John F. Kennedy",
        "stepNum": 1
    },
    "single_trivia_dev_3635": {
        "option": "C",
        "prediction": "Jewish culture",
        "stepNum": 2
    },
    "single_trivia_dev_3669": {
        "option": "A",
        "prediction": "Johann Strauss II",
        "stepNum": 0
    },
    "single_trivia_dev_3672": {
        "option": "C",
        "prediction": "Athens, Greece",
        "stepNum": 3
    },
    "single_trivia_dev_3686": {
        "option": "B",
        "prediction": "Mensa International",
        "stepNum": 1
    },
    "single_trivia_dev_3709": {
        "option": "B",
        "prediction": "stars",
        "stepNum": 1
    },
    "single_trivia_dev_371": {
        "option": "C",
        "prediction": "United Artists",
        "stepNum": 3
    },
    "single_trivia_dev_3753": {
        "option": "B",
        "prediction": "540",
        "stepNum": 1
    },
    "single_trivia_dev_3810": {
        "option": "B",
        "prediction": "a creature of extraordinary beauty believed to live in fountains, rivers, waterfalls or forested regions with pure water",
        "stepNum": 1
    },
    "single_trivia_dev_3811": {
        "option": "A",
        "prediction": "A Chinese-inspired meat dumpling-style snack food that normally consists of a large ball of pork or other meat, cabbage and flavourings, encased in a wrapper similar to that of a more traditional dumpling is a wonton. However, a wonton is a small dumpling. A wonton is not a large ball of meat. A large ball of meat is a wonton's cousin, a wonton's relative, a wonton's similar food, a wonton's similar snack food",
        "stepNum": 0
    },
    "single_trivia_dev_3828": {
        "option": "B",
        "prediction": "humming",
        "stepNum": 1
    },
    "single_trivia_dev_3842": {
        "option": "C",
        "prediction": "Elton John",
        "stepNum": 2
    },
    "single_trivia_dev_3850": {
        "option": "B",
        "prediction": "John Keats",
        "stepNum": 1
    },
    "single_trivia_dev_3871": {
        "option": "A",
        "prediction": "The Adventures of Twizzle",
        "stepNum": 0
    },
    "single_trivia_dev_3875": {
        "option": "B",
        "prediction": "spirit level",
        "stepNum": 1
    },
    "single_trivia_dev_3893": {
        "option": "A",
        "prediction": "the Western Wall",
        "stepNum": 0
    },
    "single_trivia_dev_3894": {
        "option": "B",
        "prediction": "Anders Dahl",
        "stepNum": 1
    },
    "single_trivia_dev_3908": {
        "option": "B",
        "prediction": "Katy Perry",
        "stepNum": 1
    },
    "single_trivia_dev_391": {
        "option": "A",
        "prediction": "25",
        "stepNum": 0
    },
    "single_trivia_dev_3918": {
        "option": "B",
        "prediction": "Bedford Falls",
        "stepNum": 1
    },
    "single_trivia_dev_3922": {
        "option": "B",
        "prediction": "The leaves of the plant \\\"Dendrocnide moroides\\\" (gympie-gympie) cause an extremely painful stinging sensation. The leaves of the plant \\\"Dendrocnide moroides\\\" do not relieve pain caused by stinging nettle. The leaves of the plant \\\"Urtica dioica\\\" (stinging nettle) cause an extremely painful stinging sensation. The leaves of the plant \\\"Urtica dioica\\\" do not relieve pain",
        "stepNum": 1
    },
    "single_trivia_dev_3943": {
        "option": "A",
        "prediction": "Russia, Georgia, Azerbaijan, Armenia, and Turkey",
        "stepNum": 0
    },
    "single_trivia_dev_3948": {
        "option": "B",
        "prediction": "Jules",
        "stepNum": 1
    },
    "single_trivia_dev_3953": {
        "option": "A",
        "prediction": "Wilkie Collins",
        "stepNum": 0
    },
    "single_trivia_dev_396": {
        "option": "B",
        "prediction": "Hale & Pace",
        "stepNum": 1
    },
    "single_trivia_dev_3967": {
        "option": "B",
        "prediction": "Scandinavia",
        "stepNum": 1
    },
    "single_trivia_dev_3971": {
        "option": "C",
        "prediction": "Japan",
        "stepNum": 2
    },
    "single_trivia_dev_3985": {
        "option": "A",
        "prediction": "The Legend of Sleepy Hollow",
        "stepNum": 0
    },
    "single_trivia_dev_4000": {
        "option": "B",
        "prediction": "Anthony Buckeridge",
        "stepNum": 1
    },
    "single_trivia_dev_4025": {
        "option": "A",
        "prediction": "Nicaragua",
        "stepNum": 0
    },
    "single_trivia_dev_4072": {
        "option": "B",
        "prediction": "International Slow Food Movement",
        "stepNum": 1
    },
    "single_trivia_dev_4076": {
        "option": "B",
        "prediction": "rectangle",
        "stepNum": 1
    },
    "single_trivia_dev_4085": {
        "option": "B",
        "prediction": "flappers",
        "stepNum": 1
    },
    "single_trivia_dev_4089": {
        "option": "B",
        "prediction": "University of Oxford",
        "stepNum": 1
    },
    "single_trivia_dev_4095": {
        "option": "B",
        "prediction": "the 1967 International and Universal Exposition",
        "stepNum": 1
    },
    "single_trivia_dev_4208": {
        "option": "B",
        "prediction": "Denmark",
        "stepNum": 1
    },
    "single_trivia_dev_4212": {
        "option": "B",
        "prediction": "Shawshank Prison",
        "stepNum": 1
    },
    "single_trivia_dev_4231": {
        "option": "B",
        "prediction": "36",
        "stepNum": 1
    },
    "single_trivia_dev_4269": {
        "option": "A",
        "prediction": "Sirius",
        "stepNum": 0
    },
    "single_trivia_dev_4282": {
        "option": "B",
        "prediction": "your kneecap",
        "stepNum": 1
    },
    "single_trivia_dev_4292": {
        "option": "A",
        "prediction": "Robert De Niro",
        "stepNum": 0
    },
    "single_trivia_dev_4332": {
        "option": "B",
        "prediction": "Malibu",
        "stepNum": 1
    },
    "single_trivia_dev_4386": {
        "option": "B",
        "prediction": "Charlie Chaplin",
        "stepNum": 1
    },
    "single_trivia_dev_4409": {
        "option": "B",
        "prediction": "Thin Mints",
        "stepNum": 1
    },
    "single_trivia_dev_4419": {
        "option": "C",
        "prediction": "Phoenix",
        "stepNum": 2
    },
    "single_trivia_dev_4425": {
        "option": "B",
        "prediction": "Spanish moss",
        "stepNum": 1
    },
    "single_trivia_dev_4453": {
        "option": "B",
        "prediction": "Gone with the Wind",
        "stepNum": 1
    },
    "single_trivia_dev_4465": {
        "option": "A",
        "prediction": "Rochdale",
        "stepNum": 0
    },
    "single_trivia_dev_4479": {
        "option": "B",
        "prediction": "Holmfirth",
        "stepNum": 1
    },
    "single_trivia_dev_448": {
        "option": "A",
        "prediction": "Rugby",
        "stepNum": 0
    },
    "single_trivia_dev_451": {
        "option": "B",
        "prediction": "Texas",
        "stepNum": 1
    },
    "single_trivia_dev_4519": {
        "option": "B",
        "prediction": "Top Gun",
        "stepNum": 1
    },
    "single_trivia_dev_4533": {
        "option": "A",
        "prediction": "Whippet",
        "stepNum": 0
    },
    "single_trivia_dev_4549": {
        "option": "B",
        "prediction": "Victory Mansions",
        "stepNum": 1
    },
    "single_trivia_dev_4550": {
        "option": "B",
        "prediction": "Rigoletto",
        "stepNum": 1
    },
    "single_trivia_dev_4553": {
        "option": "B",
        "prediction": "Harold Godwinson",
        "stepNum": 1
    },
    "single_trivia_dev_4576": {
        "option": "B",
        "prediction": "15",
        "stepNum": 1
    },
    "single_trivia_dev_4578": {
        "option": "B",
        "prediction": "Alan Partridge",
        "stepNum": 1
    },
    "single_trivia_dev_4599": {
        "option": "B",
        "prediction": "In the 17th century, Christmas celebrations in England involved Carnival-like behavior including role inversion, heavy drinking, and sexual liberties. The earliest years of the Plymouth Colony were troubled with non-Puritans attempting to make merry, and Governor William Bradford was forced to reprimand offenders. English laws suppressing the holiday were enacted in 1647. In 1659, a Massachusetts law punished offenders with a hefty five shilling fine. Laws suppressing the celebration of Christmas were repealed in 1681",
        "stepNum": 1
    },
    "single_trivia_dev_462": {
        "option": "B",
        "prediction": "four",
        "stepNum": 1
    },
    "single_trivia_dev_4624": {
        "option": "A",
        "prediction": "Porsche",
        "stepNum": 0
    },
    "single_trivia_dev_4637": {
        "option": "A",
        "prediction": "Sheppey",
        "stepNum": 0
    },
    "single_trivia_dev_4645": {
        "option": "B",
        "prediction": "electric potential energy",
        "stepNum": 1
    },
    "single_trivia_dev_4665": {
        "option": "B",
        "prediction": "choux pastry",
        "stepNum": 1
    },
    "single_trivia_dev_4668": {
        "option": "B",
        "prediction": "The Dow Jones Global Indexes (DJGI) is a family of international equity indexes, including world, region, and country indexes and economic sector, market sector, industry-group, and subgroup indexes created by Dow Jones Indexes a unit of Dow Jones & Company. The indexes are constructed and weighted using capitalization weighting. They provide 95 percent market capitalization coverage of developed markets and emerging markets. More than 3000 DJGI indexes provide data on more than 5500 companies around the world",
        "stepNum": 1
    },
    "single_trivia_dev_4680": {
        "option": "B",
        "prediction": "None",
        "stepNum": 1
    },
    "single_trivia_dev_4697": {
        "option": "C",
        "prediction": "Turkish Delight",
        "stepNum": 2
    },
    "single_trivia_dev_4722": {
        "option": "B",
        "prediction": "Oklahoma",
        "stepNum": 1
    },
    "single_trivia_dev_4731": {
        "option": "B",
        "prediction": "Tampa Bay",
        "stepNum": 1
    },
    "single_trivia_dev_4736": {
        "option": "B",
        "prediction": "Netherlands",
        "stepNum": 1
    },
    "single_trivia_dev_4748": {
        "option": "B",
        "prediction": "Zhukov",
        "stepNum": 1
    },
    "single_trivia_dev_4791": {
        "option": "B",
        "prediction": "Ardennes",
        "stepNum": 1
    },
    "single_trivia_dev_4793": {
        "option": "B",
        "prediction": "Paris",
        "stepNum": 1
    },
    "single_trivia_dev_4797": {
        "option": "B",
        "prediction": "Charlie Magri",
        "stepNum": 1
    },
    "single_trivia_dev_4804": {
        "option": "B",
        "prediction": "Henry IV of England",
        "stepNum": 1
    },
    "single_trivia_dev_4821": {
        "option": "B",
        "prediction": "Sydney Harbour Bridge",
        "stepNum": 1
    },
    "single_trivia_dev_4824": {
        "option": "A",
        "prediction": "hunchback",
        "stepNum": 0
    },
    "single_trivia_dev_4827": {
        "option": "C",
        "prediction": "Chile",
        "stepNum": 6
    },
    "single_trivia_dev_4841": {
        "option": "B",
        "prediction": "Queen Anne",
        "stepNum": 1
    },
    "single_trivia_dev_4872": {
        "option": "B",
        "prediction": "Birmingham",
        "stepNum": 1
    },
    "single_trivia_dev_491": {
        "option": "C",
        "prediction": "None",
        "stepNum": 2
    },
    "single_trivia_dev_4910": {
        "option": "A",
        "prediction": "Joe Meek",
        "stepNum": 0
    },
    "single_trivia_dev_4950": {
        "option": "B",
        "prediction": "Overdrive",
        "stepNum": 1
    },
    "single_trivia_dev_4963": {
        "option": "A",
        "prediction": "Twelfth Night",
        "stepNum": 0
    },
    "single_trivia_dev_4993": {
        "option": "B",
        "prediction": "Paul C\\u00e9zanne",
        "stepNum": 1
    },
    "single_trivia_dev_5052": {
        "option": "C",
        "prediction": "F. Scott Fitzgerald",
        "stepNum": 2
    },
    "single_trivia_dev_5053": {
        "option": "B",
        "prediction": "music videos",
        "stepNum": 1
    },
    "single_trivia_dev_5102": {
        "option": "B",
        "prediction": "Juneau",
        "stepNum": 1
    },
    "single_trivia_dev_5113": {
        "option": "A",
        "prediction": "Edward II",
        "stepNum": 0
    },
    "single_trivia_dev_5129": {
        "option": "B",
        "prediction": "The four Inns of Court in London, together with the associated Inns of Chancery, formed a recognised centre of legal and intellectual education, and \\u2013 although never a university in any technical sense \\u2013 were sometimes collectively described in the early modern period as England's \\\"third university\\\". Most notably, this claim was made in Sir George Buck's tract, \\\"The Third Universitie of England: Or a Treatise of the Foundations of all the Colledges, Auncient Schooles of Priviledge, and of Houses of Learning, and Liberall Arts, within and about the Most",
        "stepNum": 1
    },
    "single_trivia_dev_5138": {
        "option": "B",
        "prediction": "King John",
        "stepNum": 1
    },
    "single_trivia_dev_5140": {
        "option": "B",
        "prediction": "Jacques Villeneuve",
        "stepNum": 1
    },
    "single_trivia_dev_5195": {
        "option": "B",
        "prediction": "The New Yardbirds",
        "stepNum": 1
    },
    "single_trivia_dev_5216": {
        "option": "B",
        "prediction": "Gilbert",
        "stepNum": 1
    },
    "single_trivia_dev_5248": {
        "option": "B",
        "prediction": "Deepwater Horizon",
        "stepNum": 1
    },
    "single_trivia_dev_5265": {
        "option": "B",
        "prediction": "1460s",
        "stepNum": 1
    },
    "single_trivia_dev_5266": {
        "option": "B",
        "prediction": "The Equals",
        "stepNum": 1
    },
    "single_trivia_dev_5267": {
        "option": "B",
        "prediction": "titanium",
        "stepNum": 1
    },
    "single_trivia_dev_5277": {
        "option": "B",
        "prediction": "Miriam",
        "stepNum": 1
    },
    "single_trivia_dev_5281": {
        "option": "B",
        "prediction": "harlequin costume",
        "stepNum": 1
    },
    "single_trivia_dev_5291": {
        "option": "B",
        "prediction": "Roy Lichtenstein",
        "stepNum": 1
    },
    "single_trivia_dev_530": {
        "option": "B",
        "prediction": "Stone of Scone",
        "stepNum": 1
    },
    "single_trivia_dev_5307": {
        "option": "A",
        "prediction": "Turdidae",
        "stepNum": 0
    },
    "single_trivia_dev_5339": {
        "option": "B",
        "prediction": "Beaumaris, Anglesey, Wales",
        "stepNum": 1
    },
    "single_trivia_dev_5371": {
        "option": "A",
        "prediction": "The Man Who Knew Too Much",
        "stepNum": 0
    },
    "single_trivia_dev_5389": {
        "option": "B",
        "prediction": "rook",
        "stepNum": 1
    },
    "single_trivia_dev_539": {
        "option": "B",
        "prediction": "The Fat Duck",
        "stepNum": 1
    },
    "single_trivia_dev_5399": {
        "option": "C",
        "prediction": "County Donegal",
        "stepNum": 2
    },
    "single_trivia_dev_5426": {
        "option": "C",
        "prediction": "ern or erne",
        "stepNum": 3
    },
    "single_trivia_dev_5441": {
        "option": "B",
        "prediction": "James Callaghan",
        "stepNum": 1
    },
    "single_trivia_dev_5451": {
        "option": "B",
        "prediction": "\\\"Sixteen Tons\\\" is not the answer",
        "stepNum": 1
    },
    "single_trivia_dev_5462": {
        "option": "B",
        "prediction": "Foreign Secretary",
        "stepNum": 1
    },
    "single_trivia_dev_5472": {
        "option": "B",
        "prediction": "there is no answer",
        "stepNum": 1
    },
    "single_trivia_dev_549": {
        "option": "B",
        "prediction": "Au",
        "stepNum": 1
    },
    "single_trivia_dev_5547": {
        "option": "B",
        "prediction": "Isabella",
        "stepNum": 1
    },
    "single_trivia_dev_555": {
        "option": "B",
        "prediction": "343",
        "stepNum": 1
    },
    "single_trivia_dev_5560": {
        "option": "B",
        "prediction": "Elizabeth Tower",
        "stepNum": 1
    },
    "single_trivia_dev_5569": {
        "option": "B",
        "prediction": "Frankfort",
        "stepNum": 1
    },
    "single_trivia_dev_5612": {
        "option": "A",
        "prediction": "Billy Connolly",
        "stepNum": 0
    },
    "single_trivia_dev_5624": {
        "option": "A",
        "prediction": "Peter Mayle",
        "stepNum": 0
    },
    "single_trivia_dev_5627": {
        "option": "C",
        "prediction": "Los Angeles",
        "stepNum": 2
    },
    "single_trivia_dev_5631": {
        "option": "B",
        "prediction": "Les Mis\\u00e9rables",
        "stepNum": 1
    },
    "single_trivia_dev_5634": {
        "option": "A",
        "prediction": "bluebell",
        "stepNum": 0
    },
    "single_trivia_dev_5654": {
        "option": "B",
        "prediction": "Tanzania",
        "stepNum": 1
    },
    "single_trivia_dev_5656": {
        "option": "B",
        "prediction": "Tears for Fears",
        "stepNum": 1
    },
    "single_trivia_dev_5695": {
        "option": "B",
        "prediction": "Grendel",
        "stepNum": 1
    },
    "single_trivia_dev_5752": {
        "option": "B",
        "prediction": "Judas son of James",
        "stepNum": 1
    },
    "single_trivia_dev_5766": {
        "option": "C",
        "prediction": "Iain Duncan Smith",
        "stepNum": 2
    },
    "single_trivia_dev_5768": {
        "option": "A",
        "prediction": "Fats Waller",
        "stepNum": 0
    },
    "single_trivia_dev_5788": {
        "option": "C",
        "prediction": "Braine-l'Alleud, Belgium",
        "stepNum": 3
    },
    "single_trivia_dev_5790": {
        "option": "B",
        "prediction": "Ralph Vaughan Williams",
        "stepNum": 1
    },
    "single_trivia_dev_5816": {
        "option": "B",
        "prediction": "Griflet",
        "stepNum": 1
    },
    "single_trivia_dev_5819": {
        "option": "B",
        "prediction": "Jeremiah",
        "stepNum": 1
    },
    "single_trivia_dev_5827": {
        "option": "B",
        "prediction": "a fouled anchor",
        "stepNum": 1
    },
    "single_trivia_dev_5837": {
        "option": "B",
        "prediction": "Ishmael",
        "stepNum": 1
    },
    "single_trivia_dev_5838": {
        "option": "B",
        "prediction": "Geraldine McQueen",
        "stepNum": 1
    },
    "single_trivia_dev_5840": {
        "option": "A",
        "prediction": "follicle",
        "stepNum": 0
    },
    "single_trivia_dev_5858": {
        "option": "A",
        "prediction": "honeysuckle",
        "stepNum": 0
    },
    "single_trivia_dev_5933": {
        "option": "B",
        "prediction": "There is no answer",
        "stepNum": 1
    },
    "single_trivia_dev_5935": {
        "option": "B",
        "prediction": "Sir Edward Grey",
        "stepNum": 1
    },
    "single_trivia_dev_5948": {
        "option": "B",
        "prediction": "Queens",
        "stepNum": 1
    },
    "single_trivia_dev_596": {
        "option": "B",
        "prediction": "There is no answer",
        "stepNum": 1
    },
    "single_trivia_dev_5999": {
        "option": "A",
        "prediction": "Romania",
        "stepNum": 0
    },
    "single_trivia_dev_6002": {
        "option": "B",
        "prediction": "Palace of Westminster",
        "stepNum": 1
    },
    "single_trivia_dev_603": {
        "option": "A",
        "prediction": "Argentina",
        "stepNum": 0
    },
    "single_trivia_dev_6032": {
        "option": "B",
        "prediction": "Burton upon Trent",
        "stepNum": 1
    },
    "single_trivia_dev_6044": {
        "option": "A",
        "prediction": "Popeye",
        "stepNum": 0
    },
    "single_trivia_dev_6050": {
        "option": "B",
        "prediction": "Bubba Watson",
        "stepNum": 1
    },
    "single_trivia_dev_6055": {
        "option": "B",
        "prediction": "1920s",
        "stepNum": 1
    },
    "single_trivia_dev_6080": {
        "option": "A",
        "prediction": "sun of York",
        "stepNum": 0
    },
    "single_trivia_dev_6090": {
        "option": "B",
        "prediction": "Billie Holiday",
        "stepNum": 1
    },
    "single_trivia_dev_6102": {
        "option": "B",
        "prediction": "Yemen",
        "stepNum": 1
    },
    "single_trivia_dev_6140": {
        "option": "B",
        "prediction": "Worcester",
        "stepNum": 1
    },
    "single_trivia_dev_6143": {
        "option": "B",
        "prediction": "Wiltshire",
        "stepNum": 1
    },
    "single_trivia_dev_6148": {
        "option": "C",
        "prediction": "Chelmsford",
        "stepNum": 2
    },
    "single_trivia_dev_6155": {
        "option": "A",
        "prediction": "Pyrenees",
        "stepNum": 0
    },
    "single_trivia_dev_6188": {
        "option": "B",
        "prediction": "Richard III",
        "stepNum": 1
    },
    "single_trivia_dev_6189": {
        "option": "B",
        "prediction": "Pony Express",
        "stepNum": 1
    },
    "single_trivia_dev_6193": {
        "option": "B",
        "prediction": "None",
        "stepNum": 1
    },
    "single_trivia_dev_6249": {
        "option": "B",
        "prediction": "at the end of time and matter",
        "stepNum": 1
    },
    "single_trivia_dev_6251": {
        "option": "A",
        "prediction": "Halifax",
        "stepNum": 0
    },
    "single_trivia_dev_6268": {
        "option": "B",
        "prediction": "Henry VIII",
        "stepNum": 1
    },
    "single_trivia_dev_6285": {
        "option": "B",
        "prediction": "workshop",
        "stepNum": 1
    },
    "single_trivia_dev_629": {
        "option": "A",
        "prediction": "given birth",
        "stepNum": 0
    },
    "single_trivia_dev_630": {
        "option": "B",
        "prediction": "there is no information about the President of Granada who was executed during the 1983 coup",
        "stepNum": 1
    },
    "single_trivia_dev_6317": {
        "option": "B",
        "prediction": "The Listeners",
        "stepNum": 1
    },
    "single_trivia_dev_6323": {
        "option": "B",
        "prediction": "18th",
        "stepNum": 1
    },
    "single_trivia_dev_6363": {
        "option": "B",
        "prediction": "Caractacus Potts",
        "stepNum": 1
    },
    "single_trivia_dev_6365": {
        "option": "B",
        "prediction": "Laurel and Hardy",
        "stepNum": 1
    },
    "single_trivia_dev_6383": {
        "option": "A",
        "prediction": "Bayern Munich",
        "stepNum": 0
    },
    "single_trivia_dev_644": {
        "option": "B",
        "prediction": "Spain",
        "stepNum": 1
    },
    "single_trivia_dev_6476": {
        "option": "B",
        "prediction": "not mentioned",
        "stepNum": 1
    },
    "single_trivia_dev_6478": {
        "option": "B",
        "prediction": "10",
        "stepNum": 1
    },
    "single_trivia_dev_648": {
        "option": "B",
        "prediction": "Iceland",
        "stepNum": 1
    },
    "single_trivia_dev_6501": {
        "option": "C",
        "prediction": "smoke",
        "stepNum": 2
    },
    "single_trivia_dev_6518": {
        "option": "C",
        "prediction": "Kanyadaan",
        "stepNum": 3
    },
    "single_trivia_dev_6546": {
        "option": "A",
        "prediction": "Scrooge McDuck",
        "stepNum": 0
    },
    "single_trivia_dev_655": {
        "option": "B",
        "prediction": "Indiana",
        "stepNum": 1
    },
    "single_trivia_dev_6566": {
        "option": "A",
        "prediction": "Potala Palace",
        "stepNum": 0
    },
    "single_trivia_dev_6569": {
        "option": "A",
        "prediction": "L\\u00fcbeck",
        "stepNum": 0
    },
    "single_trivia_dev_658": {
        "option": "B",
        "prediction": "rabbits",
        "stepNum": 1
    },
    "single_trivia_dev_6580": {
        "option": "C",
        "prediction": "Guernica",
        "stepNum": 3
    },
    "single_trivia_dev_6597": {
        "option": "B",
        "prediction": "The topic of the only official editorial that Time ever published was the Watergate scandal. However, this is not the answer to the question. The question asks for the topic of the only official editorial that Time ever published, and the hint is that it happened in 1974. The answer to the question is: Watergate. However, this is not the answer to the question. The answer to the question is: Watergate. However, this is not the answer to the question. The answer",
        "stepNum": 1
    },
    "single_trivia_dev_6598": {
        "option": "A",
        "prediction": "Six-Day War",
        "stepNum": 0
    },
    "single_trivia_dev_6603": {
        "option": "A",
        "prediction": "same-sex behavior",
        "stepNum": 0
    },
    "single_trivia_dev_6616": {
        "option": "B",
        "prediction": "Stephen King",
        "stepNum": 1
    },
    "single_trivia_dev_663": {
        "option": "B",
        "prediction": "architect",
        "stepNum": 1
    },
    "single_trivia_dev_6637": {
        "option": "A",
        "prediction": "Gilbert N. Lewis",
        "stepNum": 0
    },
    "single_trivia_dev_6644": {
        "option": "B",
        "prediction": "disintegration due to tidal forces",
        "stepNum": 1
    },
    "single_trivia_dev_6645": {
        "option": "A",
        "prediction": "cross-section",
        "stepNum": 0
    },
    "single_trivia_dev_6649": {
        "option": "A",
        "prediction": "Jabir ibn Hayyan",
        "stepNum": 0
    },
    "single_trivia_dev_6669": {
        "option": "B",
        "prediction": "7",
        "stepNum": 1
    },
    "single_trivia_dev_6670": {
        "option": "A",
        "prediction": "University of Cambridge",
        "stepNum": 0
    },
    "single_trivia_dev_67": {
        "option": "B",
        "prediction": "Major General George S. Patton",
        "stepNum": 1
    },
    "single_trivia_dev_6703": {
        "option": "A",
        "prediction": "Surrealism",
        "stepNum": 0
    },
    "single_trivia_dev_673": {
        "option": "B",
        "prediction": "There is no answer",
        "stepNum": 1
    },
    "single_trivia_dev_6757": {
        "option": "B",
        "prediction": "Victor",
        "stepNum": 1
    },
    "single_trivia_dev_6762": {
        "option": "B",
        "prediction": "Ascot",
        "stepNum": 1
    },
    "single_trivia_dev_6766": {
        "option": "B",
        "prediction": "Termini Imerese or Termini",
        "stepNum": 1
    },
    "single_trivia_dev_6804": {
        "option": "C",
        "prediction": "Ivorian",
        "stepNum": 2
    },
    "single_trivia_dev_6824": {
        "option": "B",
        "prediction": "Clumber Spaniel",
        "stepNum": 1
    },
    "single_trivia_dev_6910": {
        "option": "C",
        "prediction": "Nepal",
        "stepNum": 2
    },
    "single_trivia_dev_6934": {
        "option": "B",
        "prediction": "Iwo Jima",
        "stepNum": 1
    },
    "single_trivia_dev_6937": {
        "option": "B",
        "prediction": "540\\u00b0",
        "stepNum": 1
    },
    "single_trivia_dev_6961": {
        "option": "C",
        "prediction": "Clint Eastwood",
        "stepNum": 2
    },
    "single_trivia_dev_6971": {
        "option": "A",
        "prediction": "long jump",
        "stepNum": 0
    },
    "single_trivia_dev_6989": {
        "option": "B",
        "prediction": "John Wayne",
        "stepNum": 1
    },
    "single_trivia_dev_699": {
        "option": "B",
        "prediction": "Enceladus",
        "stepNum": 1
    },
    "single_trivia_dev_7002": {
        "option": "B",
        "prediction": "Repton",
        "stepNum": 1
    },
    "single_trivia_dev_7023": {
        "option": "A",
        "prediction": "Vanilla",
        "stepNum": 0
    },
    "single_trivia_dev_7024": {
        "option": "B",
        "prediction": "whipping",
        "stepNum": 1
    },
    "single_trivia_dev_7027": {
        "option": "B",
        "prediction": "penguin",
        "stepNum": 1
    },
    "single_trivia_dev_7038": {
        "option": "B",
        "prediction": "green",
        "stepNum": 1
    },
    "single_trivia_dev_704": {
        "option": "A",
        "prediction": "Peru",
        "stepNum": 0
    },
    "single_trivia_dev_7053": {
        "option": "B",
        "prediction": "Wagon Train",
        "stepNum": 1
    },
    "single_trivia_dev_7054": {
        "option": "B",
        "prediction": "Macavity",
        "stepNum": 1
    },
    "single_trivia_dev_7069": {
        "option": "B",
        "prediction": "10 Rillington Place",
        "stepNum": 1
    },
    "single_trivia_dev_7071": {
        "option": "B",
        "prediction": "Gerald Ford",
        "stepNum": 1
    },
    "single_trivia_dev_7105": {
        "option": "B",
        "prediction": "Golden Earring",
        "stepNum": 1
    },
    "single_trivia_dev_7118": {
        "option": "A",
        "prediction": "entropy",
        "stepNum": 0
    },
    "single_trivia_dev_7145": {
        "option": "B",
        "prediction": "John Betjeman",
        "stepNum": 1
    },
    "single_trivia_dev_7179": {
        "option": "B",
        "prediction": "The television series 'Soldier, Soldier' was a British television drama series. The title comes from a traditional song of the same name - \\\"Soldier, soldier won't you marry me, with your musket, fife and drum?\\\" - an instrumental version of which was used as its theme music. The series featured the daily lives of a group of soldiers in 'B' Company, 1st Battalion The King's Fusiliers, a fictional British regiment. The series was created by",
        "stepNum": 1
    },
    "single_trivia_dev_7188": {
        "option": "A",
        "prediction": "South Africa",
        "stepNum": 0
    },
    "single_trivia_dev_7217": {
        "option": "B",
        "prediction": "Deep Purple",
        "stepNum": 1
    },
    "single_trivia_dev_7223": {
        "option": "A",
        "prediction": "bisque",
        "stepNum": 0
    },
    "single_trivia_dev_7250": {
        "option": "A",
        "prediction": "Betty Boop",
        "stepNum": 0
    },
    "single_trivia_dev_7254": {
        "option": "B",
        "prediction": "Hristo Stoichkov",
        "stepNum": 1
    },
    "single_trivia_dev_726": {
        "option": "B",
        "prediction": "Saudi Arabia",
        "stepNum": 1
    },
    "single_trivia_dev_7312": {
        "option": "B",
        "prediction": "Gerhard Schr\\u00f6der",
        "stepNum": 1
    },
    "single_trivia_dev_7327": {
        "option": "B",
        "prediction": "7",
        "stepNum": 1
    },
    "single_trivia_dev_7328": {
        "option": "B",
        "prediction": "Connie Fisher",
        "stepNum": 1
    },
    "single_trivia_dev_7338": {
        "option": "C",
        "prediction": "1999",
        "stepNum": 4
    },
    "single_trivia_dev_7349": {
        "option": "C",
        "prediction": "Marshalsea Debtors' Prison",
        "stepNum": 2
    },
    "single_trivia_dev_7374": {
        "option": "C",
        "prediction": "a particle",
        "stepNum": 3
    },
    "single_trivia_dev_7382": {
        "option": "A",
        "prediction": "Minnesota",
        "stepNum": 0
    },
    "single_trivia_dev_7404": {
        "option": "B",
        "prediction": "There is no answer",
        "stepNum": 1
    },
    "single_trivia_dev_7415": {
        "option": "A",
        "prediction": "Enfield Southgate",
        "stepNum": 0
    },
    "single_trivia_dev_7419": {
        "option": "B",
        "prediction": "Futurist",
        "stepNum": 1
    },
    "single_trivia_dev_7436": {
        "option": "A",
        "prediction": "African Violet",
        "stepNum": 0
    },
    "single_trivia_dev_7450": {
        "option": "A",
        "prediction": "What A Lot I Got",
        "stepNum": 0
    },
    "single_trivia_dev_7454": {
        "option": "A",
        "prediction": "Chichester",
        "stepNum": 0
    },
    "single_trivia_dev_7469": {
        "option": "B",
        "prediction": "Birmingham",
        "stepNum": 1
    },
    "single_trivia_dev_7486": {
        "option": "A",
        "prediction": "Dolmades",
        "stepNum": 0
    },
    "single_trivia_dev_7491": {
        "option": "B",
        "prediction": "Apple",
        "stepNum": 1
    },
    "single_trivia_dev_7531": {
        "option": "B",
        "prediction": "Advance Australia Fair",
        "stepNum": 1
    },
    "single_trivia_dev_7538": {
        "option": "A",
        "prediction": "The Edge",
        "stepNum": 0
    },
    "single_trivia_dev_7552": {
        "option": "B",
        "prediction": "Clotho, Lachesis, and Atropos",
        "stepNum": 1
    },
    "single_trivia_dev_7582": {
        "option": "B",
        "prediction": "Brian Blessed",
        "stepNum": 1
    },
    "single_trivia_dev_7583": {
        "option": "B",
        "prediction": "Bette Midler",
        "stepNum": 1
    },
    "single_trivia_dev_7670": {
        "option": "A",
        "prediction": "Graeme Smith",
        "stepNum": 0
    },
    "single_trivia_dev_7690": {
        "option": "B",
        "prediction": "Vietnam",
        "stepNum": 1
    },
    "single_trivia_dev_7726": {
        "option": "B",
        "prediction": "Saturday",
        "stepNum": 1
    },
    "single_trivia_dev_7727": {
        "option": "B",
        "prediction": "500 euro note",
        "stepNum": 1
    },
    "single_trivia_dev_7739": {
        "option": "B",
        "prediction": "Terry Waite",
        "stepNum": 1
    },
    "single_trivia_dev_7765": {
        "option": "B",
        "prediction": "Gosford Park",
        "stepNum": 1
    },
    "single_trivia_dev_7778": {
        "option": "B",
        "prediction": "rhombus",
        "stepNum": 1
    },
    "single_trivia_dev_7780": {
        "option": "A",
        "prediction": "In the Name of the Father",
        "stepNum": 0
    },
    "single_trivia_dev_7805": {
        "option": "B",
        "prediction": "Oh Boy!",
        "stepNum": 1
    },
    "single_trivia_dev_7820": {
        "option": "B",
        "prediction": "Mr. Rumbold",
        "stepNum": 1
    },
    "single_trivia_dev_7838": {
        "option": "B",
        "prediction": "10,000",
        "stepNum": 1
    },
    "single_trivia_dev_7842": {
        "option": "B",
        "prediction": "There is no information about Thomas Huntley-Wood in the provided text. However, there is information about Joseph Huntley, who was a 19th-century biscuit maker and innovator, who lived in the English town of Reading. In 1822 he founded a small biscuit shop in a metal tin. Out of this innovation grew two businesses: Joseph (the elder's) biscuit shop that was to become the famous biscuit manufacturer Huntley & Palmers, and Huntley,",
        "stepNum": 1
    },
    "single_trivia_dev_7847": {
        "option": "B",
        "prediction": "Caroline Quentin",
        "stepNum": 1
    },
    "single_trivia_dev_7854": {
        "option": "B",
        "prediction": "Morecambe Bay",
        "stepNum": 1
    },
    "single_trivia_dev_7864": {
        "option": "B",
        "prediction": "The Ring",
        "stepNum": 1
    },
    "single_trivia_dev_7903": {
        "option": "B",
        "prediction": "$10",
        "stepNum": 1
    },
    "single_trivia_dev_796": {
        "option": "C",
        "prediction": "Friday the 13th",
        "stepNum": 2
    },
    "single_trivia_dev_7967": {
        "option": "B",
        "prediction": "fruit flies like a banana",
        "stepNum": 1
    },
    "single_trivia_dev_8027": {
        "option": "B",
        "prediction": "Paavo Nurmi",
        "stepNum": 1
    },
    "single_trivia_dev_8033": {
        "option": "B",
        "prediction": "Doro Pesch",
        "stepNum": 1
    },
    "single_trivia_dev_8034": {
        "option": "B",
        "prediction": "Will Sergeant",
        "stepNum": 1
    },
    "single_trivia_dev_8085": {
        "option": "B",
        "prediction": "bedding plants",
        "stepNum": 1
    },
    "single_trivia_dev_8099": {
        "option": "B",
        "prediction": "self-deliverance",
        "stepNum": 1
    },
    "single_trivia_dev_8117": {
        "option": "B",
        "prediction": "club feet",
        "stepNum": 1
    },
    "single_trivia_dev_8124": {
        "option": "B",
        "prediction": "There are several Princess Alexandra's in the list. Princess Alexandra of Luxembourg was married to Prince Guillaume of Luxembourg. Princess Alexandra of Sayn-Wittgenstein-Berleburg was married to Count Jefferson von Pfeil und Klein-Ellguth. Princess Alexandra of Saxe-Altenburg was married to Grand Duke Konstantin Nikolayevich of Russia. Princess Alexandra of Schleswig-Holstein was married to Douglas Barton-Miller. Princess Alexandra of Bavaria was not married",
        "stepNum": 1
    },
    "single_trivia_dev_8197": {
        "option": "B",
        "prediction": "Bayern Munich",
        "stepNum": 1
    },
    "single_trivia_dev_8223": {
        "option": "B",
        "prediction": "1931",
        "stepNum": 1
    },
    "single_trivia_dev_829": {
        "option": "A",
        "prediction": "Magic Lantern",
        "stepNum": 0
    },
    "single_trivia_dev_8295": {
        "option": "A",
        "prediction": "the night",
        "stepNum": 0
    },
    "single_trivia_dev_8310": {
        "option": "A",
        "prediction": "Croatia",
        "stepNum": 0
    },
    "single_trivia_dev_8323": {
        "option": "B",
        "prediction": "A Hard Day's Night",
        "stepNum": 1
    },
    "single_trivia_dev_8334": {
        "option": "B",
        "prediction": "King James Version",
        "stepNum": 1
    },
    "single_trivia_dev_8336": {
        "option": "B",
        "prediction": "Shem, Ham, and Japheth",
        "stepNum": 1
    },
    "single_trivia_dev_8358": {
        "option": "B",
        "prediction": "50th state of the United States of America",
        "stepNum": 1
    },
    "single_trivia_dev_840": {
        "option": "A",
        "prediction": "tooth",
        "stepNum": 0
    },
    "single_trivia_dev_8405": {
        "option": "B",
        "prediction": "Advance Motor Manufacturing Company",
        "stepNum": 1
    },
    "single_trivia_dev_8423": {
        "option": "B",
        "prediction": "physician",
        "stepNum": 1
    },
    "single_trivia_dev_8427": {
        "option": "B",
        "prediction": "sugar",
        "stepNum": 1
    },
    "single_trivia_dev_8428": {
        "option": "B",
        "prediction": "Austin",
        "stepNum": 1
    },
    "single_trivia_dev_8433": {
        "option": "B",
        "prediction": "Jiang Qing",
        "stepNum": 1
    },
    "single_trivia_dev_8452": {
        "option": "A",
        "prediction": "jenny",
        "stepNum": 0
    },
    "single_trivia_dev_8472": {
        "option": "A",
        "prediction": "SpongeBob SquarePants",
        "stepNum": 0
    },
    "single_trivia_dev_8543": {
        "option": "C",
        "prediction": "Mickey Mouse",
        "stepNum": 2
    },
    "single_trivia_dev_8553": {
        "option": "B",
        "prediction": "Virginia, Massachusetts, New Hampshire, Maryland, Connecticut, Rhode Island, Delaware, North Carolina, South Carolina, New York, New Jersey, Pennsylvania, and Georgia",
        "stepNum": 1
    },
    "single_trivia_dev_8555": {
        "option": "B",
        "prediction": "Mayflower",
        "stepNum": 1
    },
    "single_trivia_dev_8562": {
        "option": "B",
        "prediction": "telegraph",
        "stepNum": 1
    },
    "single_trivia_dev_8563": {
        "option": "B",
        "prediction": "Andrew Johnson",
        "stepNum": 1
    },
    "single_trivia_dev_8569": {
        "option": "B",
        "prediction": "AB",
        "stepNum": 1
    },
    "single_trivia_dev_8582": {
        "option": "B",
        "prediction": "Gradual",
        "stepNum": 1
    },
    "single_trivia_dev_8597": {
        "option": "A",
        "prediction": "Tony Awards",
        "stepNum": 0
    },
    "single_trivia_dev_8605": {
        "option": "A",
        "prediction": "The Twilight Zone",
        "stepNum": 0
    },
    "single_trivia_dev_863": {
        "option": "B",
        "prediction": "Julian Clary",
        "stepNum": 1
    },
    "single_trivia_dev_8632": {
        "option": "B",
        "prediction": "Franklin D. Roosevelt",
        "stepNum": 1
    },
    "single_trivia_dev_8637": {
        "option": "A",
        "prediction": "1 wood",
        "stepNum": 0
    },
    "single_trivia_dev_8670": {
        "option": "B",
        "prediction": "mountain landform",
        "stepNum": 1
    },
    "single_trivia_dev_8684": {
        "option": "A",
        "prediction": "False",
        "stepNum": 0
    },
    "single_trivia_dev_8699": {
        "option": "C",
        "prediction": "Criss Angel",
        "stepNum": 3
    },
    "single_trivia_dev_8706": {
        "option": "B",
        "prediction": "Pinocchio",
        "stepNum": 1
    },
    "single_trivia_dev_8708": {
        "option": "A",
        "prediction": "Terra Incognita",
        "stepNum": 0
    },
    "single_trivia_dev_8710": {
        "option": "B",
        "prediction": "sapphire",
        "stepNum": 1
    },
    "single_trivia_dev_8728": {
        "option": "C",
        "prediction": "1949",
        "stepNum": 3
    },
    "single_trivia_dev_8729": {
        "option": "A",
        "prediction": "Burger King",
        "stepNum": 0
    },
    "single_trivia_dev_8757": {
        "option": "C",
        "prediction": "bed bug",
        "stepNum": 2
    },
    "single_trivia_dev_8770": {
        "option": "B",
        "prediction": "face-off",
        "stepNum": 1
    },
    "single_trivia_dev_8774": {
        "option": "B",
        "prediction": "white",
        "stepNum": 1
    },
    "single_trivia_dev_8792": {
        "option": "B",
        "prediction": "Warner Bros",
        "stepNum": 1
    },
    "single_trivia_dev_8794": {
        "option": "B",
        "prediction": "bicycles",
        "stepNum": 1
    },
    "single_trivia_dev_88": {
        "option": "B",
        "prediction": "Kevin Costner",
        "stepNum": 1
    },
    "single_trivia_dev_8800": {
        "option": "C",
        "prediction": "Mars, Incorporated",
        "stepNum": 2
    },
    "single_trivia_dev_8801": {
        "option": "B",
        "prediction": "Honda",
        "stepNum": 1
    },
    "single_trivia_dev_8804": {
        "option": "C",
        "prediction": "Dallas",
        "stepNum": 3
    },
    "single_trivia_dev_8811": {
        "option": "B",
        "prediction": "52 white keys and 36 black keys",
        "stepNum": 1
    },
    "single_trivia_dev_8817": {
        "option": "B",
        "prediction": "Titans",
        "stepNum": 1
    },
    "single_trivia_dev_897": {
        "option": "B",
        "prediction": "None",
        "stepNum": 1
    },
    "single_trivia_dev_909": {
        "option": "B",
        "prediction": "Wendy's",
        "stepNum": 1
    },
    "single_trivia_dev_955": {
        "option": "B",
        "prediction": "Atlantic Ocean",
        "stepNum": 1
    },
    "single_trivia_dev_971": {
        "option": "B",
        "prediction": "1930",
        "stepNum": 1
    }
}